cf3/__init__.py
cf3/cf3.py
cf3-0.1.2.dist-info/entry_points.txt
cf3-0.1.2.dist-info/WHEEL
cf3-0.1.2.dist-info/METADATA
cf3-0.1.2.dist-info/RECORD
