Metadata-Version: 2.1
Name: cf3
Version: 0.1.2
Summary: Calculate the CF3 hashes for an html page
Home-page: https://github.com/ainghazal/cf3
License: Public Domain
Keywords: censorship,fingerprint
Author: Ain Ghazal
Author-email: ainghazal42@gmail.com
Requires-Python: >=3.10,<4.0
Classifier: License :: Other/Proprietary License
Classifier: Programming Language :: Python :: 3
Classifier: Programming Language :: Python :: 3.10
Requires-Dist: lxml (>=4.9.1,<5.0.0)
Project-URL: Repository, https://github.com/ainghazal/cf3
